[
  {
    "prospectId": 5001,
    "deals": [
      {
        "DealId": 10001,
        "InstructionRef": "HLX-10001-10001",
        "ProspectId": 5001,
        "Passcode": "P1001",
        "ServiceDescription": "Advice and resolution for a business contract dispute.",
        "Amount": 2500,
        "AreaOfWork": "commercial",
        "PitchedBy": "LZ",
        "PitchedDate": "2025-07-01",
        "PitchedTime": "10:00:00",
        "PitchValidUntil": "2025-07-31",
        "Status": "pitched",
        "IsMultiClient": false,
        "LeadClientId": 5001,
        "LeadClientEmail": "lead1@example.com",
        "CloseDate": null,
        "CloseTime": null,
        "jointClients": [],
        "documents": []
      }
    ],
    "jointClients": [],
    "instructions": [
      {
        "InstructionRef": "HLX-10001-10001",
        "Stage": "initialised",
        "ClientType": "Individual",
        "HelixContact": "LZ",
        "ConsentGiven": true,
        "InternalStatus": "instruction",
        "SubmissionDate": "2025-07-01",
        "SubmissionTime": "10:05:00",
        "LastUpdated": "2025-07-01T10:05:00",
        "ClientId": null,
        "RelatedClientId": null,
        "MatterId": null,
        "Title": null,
        "FirstName": "Emma",
        "LastName": "Example",
        "Nationality": "United Kingdom",
        "NationalityAlpha2": "GB",
        "DOB": "1985-05-05",
        "Gender": "Female",
        "Phone": "0101010101",
        "Email": "lead1@example.com",
        "PassportNumber": null,
        "DriversLicenseNumber": null,
        "IdType": null,
        "HouseNumber": null,
        "Street": null,
        "City": null,
        "County": null,
        "Postcode": null,
        "Country": null,
        "CountryCode": null,
        "CompanyName": null,
        "CompanyNumber": null,
        "CompanyHouseNumber": null,
        "CompanyStreet": null,
        "CompanyCity": null,
        "CompanyCounty": null,
        "CompanyPostcode": null,
        "CompanyCountry": null,
        "CompanyCountryCode": null,
        "Notes": null,
        "PaymentMethod": "card",
        "PaymentResult": null,
        "PaymentAmount": 2500,
        "PaymentProduct": "Business Contract Dispute",
        "AliasId": null,
        "OrderId": null,
        "SHASign": null,
        "PaymentTimestamp": null
      }
    ],
    "documents": [],
    "riskAssessments": [],
    "electronicIDChecks": [],
    "idVerifications": [],
    "compliance": []
  },
  {
    "prospectId": 5002,
    "deals": [
      {
        "DealId": 10002,
        "InstructionRef": "HLX-10002-10002",
        "ProspectId": 5002,
        "Passcode": "P1002",
        "ServiceDescription": "Advice on shareholder rights and corporate governance issues.",
        "Amount": 3000,
        "AreaOfWork": "commercial",
        "PitchedBy": "LZ",
        "PitchedDate": "2025-07-05",
        "PitchedTime": "11:00:00",
        "PitchValidUntil": "2025-08-05",
        "Status": "closed",
        "IsMultiClient": true,
        "LeadClientId": 5002,
        "LeadClientEmail": "lead2@example.com",
        "CloseDate": "2025-07-20",
        "CloseTime": "15:30:00",
        "jointClients": [],
        "documents": [
          {
            "DocumentId": 900021,
            "InstructionRef": "HLX-10002-10002",
            "DocumentType": null,
            "FileName": "agreement.pdf",
            "BlobUrl": "https://example.com/agreement.pdf",
            "FileSizeBytes": 152340,
            "UploadedBy": null,
            "UploadedAt": "2025-07-11T09:00:00",
            "Notes": null
          },
          {
            "DocumentId": 900022,
            "InstructionRef": "HLX-10002-10002",
            "DocumentType": null,
            "FileName": "terms.pdf",
            "BlobUrl": "https://example.com/terms.pdf",
            "FileSizeBytes": 182345,
            "UploadedBy": null,
            "UploadedAt": "2025-07-11T09:05:00",
            "Notes": null
          }
        ]
      }
    ],
    "jointClients": [
      {
        "DealJointClientId": 900012,
        "DealId": 10002,
        "ClientEmail": "joint2@example.com",
        "HasSubmitted": true,
        "SubmissionDateTime": "2025-07-12T11:00:00"
      }
    ],
    "instructions": [
      {
        "InstructionRef": "HLX-10002-10002",
        "Stage": "completed",
        "ClientType": "Individual",
        "HelixContact": "LZ",
        "ConsentGiven": true,
        "InternalStatus": "paid",
        "SubmissionDate": "2025-07-10",
        "SubmissionTime": "10:15:00",
        "LastUpdated": "2025-07-10T10:15:00",
        "ClientId": null,
        "RelatedClientId": null,
        "MatterId": null,
        "Title": null,
        "FirstName": "Alice",
        "LastName": "Anderson",
        "Nationality": "United Kingdom",
        "NationalityAlpha2": "GB",
        "DOB": "1978-02-14",
        "Gender": "Female",
        "Phone": "0202020202",
        "Email": "lead2@example.com",
        "PassportNumber": null,
        "DriversLicenseNumber": null,
        "IdType": null,
        "HouseNumber": null,
        "Street": null,
        "City": null,
        "County": null,
        "Postcode": null,
        "Country": null,
        "CountryCode": null,
        "CompanyName": null,
        "CompanyNumber": null,
        "CompanyHouseNumber": null,
        "CompanyStreet": null,
        "CompanyCity": null,
        "CompanyCounty": null,
        "CompanyPostcode": null,
        "CompanyCountry": null,
        "CompanyCountryCode": null,
        "Notes": null,
        "PaymentMethod": "card",
        "PaymentResult": "successful",
        "PaymentAmount": 3000,
        "PaymentProduct": "Shareholder Rights & Dispute Advice",
        "AliasId": null,
        "OrderId": null,
        "SHASign": null,
        "PaymentTimestamp": null
      }
    ],
    "documents": [
      {
        "DocumentId": 900021,
        "InstructionRef": "HLX-10002-10002",
        "DocumentType": null,
        "FileName": "agreement.pdf",
        "BlobUrl": "https://example.com/agreement.pdf",
        "FileSizeBytes": 152340,
        "UploadedBy": null,
        "UploadedAt": "2025-07-11T09:00:00",
        "Notes": null
      },
      {
        "DocumentId": 900022,
        "InstructionRef": "HLX-10002-10002",
        "DocumentType": null,
        "FileName": "terms.pdf",
        "BlobUrl": "https://example.com/terms.pdf",
        "FileSizeBytes": 182345,
        "UploadedBy": null,
        "UploadedAt": "2025-07-11T09:05:00",
        "Notes": null
      }
    ],
    "riskAssessments": [],
    "electronicIDChecks": [],
    "idVerifications": [],
    "compliance": []
  },
  {
    "prospectId": 5003,
    "deals": [
      {
        "DealId": 10003,
        "InstructionRef": "HLX-10003-10003",
        "ProspectId": 5003,
        "Passcode": "P1003",
        "ServiceDescription": "Advice and representation in relation to an adjudication dispute.",
        "Amount": 4000,
        "AreaOfWork": "commercial",
        "PitchedBy": "LZ",
        "PitchedDate": "2025-07-06",
        "PitchedTime": "14:00:00",
        "PitchValidUntil": "2025-08-06",
        "Status": "closed",
        "IsMultiClient": true,
        "LeadClientId": 5003,
        "LeadClientEmail": "lead3@example.com",
        "CloseDate": "2025-07-25",
        "CloseTime": "16:00:00",
        "jointClients": [],
        "documents": [
          {
            "DocumentId": 900031,
            "InstructionRef": "HLX-10003-10003",
            "DocumentType": null,
            "FileName": "evidence1.pdf",
            "BlobUrl": "https://example.com/evidence1.pdf",
            "FileSizeBytes": 258900,
            "UploadedBy": null,
            "UploadedAt": "2025-07-16T10:00:00",
            "Notes": null
          }
        ]
      }
    ],
    "jointClients": [
      {
        "DealJointClientId": 900013,
        "DealId": 10003,
        "ClientEmail": "joint3a@example.com",
        "FirstName": "Alice",
        "LastName": "Smith",
        "HasSubmitted": true,
        "SubmissionDateTime": "2025-07-15T09:00:00"
      },
      {
        "DealJointClientId": 900014,
        "DealId": 10003,
        "ClientEmail": "joint3b@example.com",
        "FirstName": "Bob",
        "LastName": "Jones",
        "HasSubmitted": true,
        "SubmissionDateTime": "2025-07-15T10:00:00"
      }
    ],
    "instructions": [
      {
        "InstructionRef": "HLX-10003-10003",
        "Stage": "completed",
        "ClientType": "Individual",
        "HelixContact": "LZ",
        "ConsentGiven": true,
        "InternalStatus": "paid",
        "SubmissionDate": "2025-07-15",
        "SubmissionTime": "14:20:00",
        "LastUpdated": "2025-07-15T14:20:00",
        "ClientId": "client-10003",
        "RelatedClientId": null,
        "MatterId": "a1a1a1a1-a1a1-4a1a-a1a1-a1a1a1a1a1a1",
        "Title": "Mr",
        "FirstName": "Bob",
        "LastName": "Bennett",
        "Nationality": "United Kingdom",
        "NationalityAlpha2": "GB",
        "DOB": "1980-03-03",
        "Gender": "Male",
        "Phone": "0303030303",
        "Email": "lead3@example.com",
        "PassportNumber": "123456789",
        "DriversLicenseNumber": "BENNE803030BB9XY",
        "IdType": "passport",
        "HouseNumber": "10",
        "Street": "Sample Street",
        "City": "London",
        "County": "Greater London",
        "Postcode": "SW1A 1AA",
        "Country": "United Kingdom",
        "CountryCode": "GB",
        "CompanyName": null,
        "CompanyNumber": null,
        "CompanyHouseNumber": null,
        "CompanyStreet": null,
        "CompanyCity": null,
        "CompanyCounty": null,
        "CompanyPostcode": null,
        "CompanyCountry": null,
        "CompanyCountryCode": null,
        "Notes": "Client confirmed ID and payment details by phone.",
        "PaymentMethod": "card",
        "PaymentResult": "successful",
        "PaymentAmount": 4000,
        "PaymentProduct": "Adjudication Advice & Dispute",
        "AliasId": "HLX10003ALIAS",
        "OrderId": "ORD10003",
        "SHASign": "9F23ABCD78234FD90AA12B345CDEF67890ABC123",
        "PaymentTimestamp": "2025-07-15T14:22:00"
      }
    ],
    "documents": [
      {
        "DocumentId": 900031,
        "InstructionRef": "HLX-10003-10003",
        "DocumentType": null,
        "FileName": "evidence1.pdf",
        "BlobUrl": "https://example.com/evidence1.pdf",
        "FileSizeBytes": 258900,
        "UploadedBy": null,
        "UploadedAt": "2025-07-16T10:00:00",
        "Notes": null
      }
    ],
    "riskAssessments": [
      {
        "MatterId": "HLX-10003-10003",
        "InstructionRef": "HLX-10003-10003",
        "RiskAssessor": "LZ",
        "ComplianceDate": "2025-07-21",
        "ComplianceExpiry": "2026-07-21",
        "ClientType": "Individual",
        "ClientType_Value": 1,
        "DestinationOfFunds": "UK bank account",
        "DestinationOfFunds_Value": 1,
        "FundsType": "Client savings",
        "FundsType_Value": 1,
        "HowWasClientIntroduced": "Online search",
        "HowWasClientIntroduced_Value": 1,
        "Limitation": "None",
        "Limitation_Value": 0,
        "SourceOfFunds": "Salary",
        "SourceOfFunds_Value": 1,
        "ValueOfInstruction": "£4,000",
        "ValueOfInstruction_Value": 1,
        "RiskAssessmentResult": "Low",
        "RiskScore": 12,
        "RiskScoreIncrementBy": 0,
        "TransactionRiskLevel": "Low",
        "ClientRiskFactorsConsidered": true,
        "TransactionRiskFactorsConsidered": true,
        "FirmWideAMLPolicyConsidered": true,
        "FirmWideSanctionsRiskConsidered": true
      }
    ],
    "electronicIDChecks": [],
    "idVerifications": [],
    "compliance": [],
    "matters": [
      {
        "MatterID": "a1a1a1a1-a1a1-4a1a-a1a1-a1a1a1a1a1a1",
        "InstructionRef": "HLX-10003-10003",
        "Status": "Open",
        "OpenDate": "2025-07-20",
        "OpenTime": "10:00:00",
        "CloseDate": null,
        "ClientID": null,
        "RelatedClientID": null,
        "DisplayNumber": "HELIX01-01",
        "ClientName": "Bob Bennett",
        "ClientType": "Individual",
        "Description": "Instruction from lead and 2 joint clients.",
        "PracticeArea": "Adjudication Advice & Dispute",
        "ApproxValue": "£4,000",
        "ResponsibleSolicitor": "Lukasz Zemanek",
        "OriginatingSolicitor": "Lukasz Zemanek",
        "SupervisingPartner": "Lukasz Zemanek",
        "Source": "referral",
        "Referrer": null,
        "method_of_contact": "email",
        "OpponentID": "B6403F65-BFA9-429D-AE33-0064D0606690",
        "OpponentSolicitorID": "CF8B9143-B101-4FF3-8534-00ADD484773C"
      }
    ],
    "opponents": [
      {
        "OpponentID": "B6403F65-BFA9-429D-AE33-0064D0606690",
        "PartyRole": "Opponent",
        "IsCompany": true,
        "Title": "Mr",
        "FirstName": "Victor",
        "LastName": "Phantom",
        "CompanyName": "Phantom Entity Ltd",
        "CompanyNumber": "AE001",
        "Email": "victor@phantom.com",
        "Phone": "01234567890",
        "HouseNumber": "1",
        "Street": "Null Road",
        "City": "Lowlight",
        "County": "Eidolonshire",
        "Postcode": "NX01 0AE",
        "Country": "United Kingdom"
      },
      {
        "OpponentID": "CF8B9143-B101-4FF3-8534-00ADD484773C",
        "PartyRole": "Opponent Solicitor",
        "IsCompany": true,
        "Title": "Mx",
        "FirstName": "Alex",
        "LastName": "Relay",
        "CompanyName": "Null Proxy LLP",
        "CompanyNumber": "AE-LAW-00X",
        "Email": "relay@nullproxy.com",
        "Phone": "01234567892",
        "HouseNumber": "3",
        "Street": "Obscura Lane",
        "City": "Lowlight",
        "County": "Eidolonshire",
        "Postcode": "NX01 0AE"
      }
    ]
  },
  {
    "prospectId": 5005,
    "deals": [
      {
        "DealId": 10005,
        "InstructionRef": "HLX-10005-10005",
        "ProspectId": 5005,
        "Passcode": "P1005",
        "ServiceDescription": "Employment tribunal representation for unfair dismissal claim.",
        "Amount": 1500,
        "AreaOfWork": "employment",
        "PitchedBy": "MK",
        "PitchedDate": "2025-07-08",
        "PitchedTime": "09:30:00",
        "PitchValidUntil": "2025-08-08",
        "Status": "closed",
        "IsMultiClient": false,
        "LeadClientId": 5004,
        "LeadClientEmail": "sarah.worker@email.com",
        "CloseDate": "2025-07-18",
        "CloseTime": "14:45:00",
        "jointClients": [],
        "documents": []
      }
    ],
    "jointClients": [],
    "instructions": [
      {
        "InstructionRef": "HLX-10005-10005",
        "Stage": "initialised",
        "ClientType": "Individual",
        "HelixContact": "MK",
        "ConsentGiven": true,
        "InternalStatus": "instruction",
        "SubmissionDate": "2025-07-18",
        "SubmissionTime": "15:00:00",
        "LastUpdated": "2025-07-18T15:00:00",
        "ClientId": null,
        "RelatedClientId": null,
        "MatterId": null,
        "Title": "Ms",
        "FirstName": "Sarah",
        "LastName": "Worker",
        "Nationality": "United Kingdom",
        "NationalityAlpha2": "GB",
        "DOB": "1990-11-22",
        "Gender": "Female",
        "Phone": "0404040404",
        "Email": "sarah.worker@email.com",
        "PassportNumber": null,
        "DriversLicenseNumber": null,
        "IdType": null,
        "HouseNumber": "42",
        "Street": "Union Street",
        "City": "Manchester",
        "County": "Greater Manchester",
        "Postcode": "M1 2AB",
        "Country": "United Kingdom",
        "CountryCode": "GB",
        "CompanyName": null,
        "CompanyNumber": null,
        "CompanyHouseNumber": null,
        "CompanyStreet": null,
        "CompanyCity": null,
        "CompanyCounty": null,
        "CompanyPostcode": null,
        "CompanyCountry": null,
        "CompanyCountryCode": null,
        "Notes": null,
        "PaymentMethod": "card",
        "PaymentResult": "successful",
        "PaymentAmount": 1500,
        "PaymentProduct": "Employment Tribunal Representation",
        "AliasId": null,
        "OrderId": null,
        "SHASign": null,
        "PaymentTimestamp": "2025-07-18T15:05:00"
      }
    ],
    "documents": [
      {
        "DocumentId": 900041,
        "InstructionRef": "HLX-10005-10005",
        "DocumentType": "employment_contract",
        "FileName": "employment_contract.pdf",
        "BlobUrl": "https://example.com/employment_contract.pdf",
        "FileSizeBytes": 245760,
        "UploadedBy": "sarah.worker@email.com",
        "UploadedAt": "2025-07-18T15:10:00",
        "Notes": "Original employment contract"
      },
      {
        "DocumentId": 900042,
        "InstructionRef": "HLX-10005-10005",
        "DocumentType": "dismissal_letter",
        "FileName": "dismissal_letter.pdf",
        "BlobUrl": "https://example.com/dismissal_letter.pdf",
        "FileSizeBytes": 89340,
        "UploadedBy": "sarah.worker@email.com",
        "UploadedAt": "2025-07-18T15:12:00",
        "Notes": "Letter of dismissal from employer"
      }
    ],
    "riskAssessments": [],
    "electronicIDChecks": [],
    "idVerifications": [],
    "compliance": []
  },
  {
    "prospectId": 5005,
    "deals": [
      {
        "DealId": 10005,
        "InstructionRef": "HLX-10005-10005",
        "ProspectId": 5005,
        "Passcode": "P1005",
        "ServiceDescription": "Property dispute resolution involving boundary disagreement.",
        "Amount": 3500,
        "AreaOfWork": "property",
        "PitchedBy": "JH",
        "PitchedDate": "2025-07-12",
        "PitchedTime": "16:00:00",
        "PitchValidUntil": "2025-08-12",
        "Status": "closed",
        "IsMultiClient": true,
        "LeadClientId": 5005,
        "LeadClientEmail": "david.property@home.co.uk",
        "CloseDate": "2025-07-19",
        "CloseTime": "11:30:00",
        "jointClients": [],
        "documents": []
      }
    ],
    "jointClients": [
      {
        "DealJointClientId": 900015,
        "DealId": 10005,
        "ClientEmail": "marie.property@home.co.uk",
        "HasSubmitted": true,
        "SubmissionDateTime": "2025-07-20T10:00:00"
      }
    ],
    "instructions": [
      {
        "InstructionRef": "HLX-10005-10005",
        "Stage": "completed",
        "ClientType": "Individual",
        "HelixContact": "JH",
        "ConsentGiven": true,
        "InternalStatus": "paid",
        "SubmissionDate": "2025-07-19",
        "SubmissionTime": "11:45:00",
        "LastUpdated": "2025-07-19T11:45:00",
        "ClientId": null,
        "RelatedClientId": null,
        "MatterId": "m5m5m5m5-m5m5-5m5m-m5m5-m5m5m5m5m5m5",
        "Title": "Mr",
        "FirstName": "David",
        "LastName": "Property",
        "Nationality": "United Kingdom",
        "NationalityAlpha2": "GB",
        "DOB": "1975-04-18",
        "Gender": "Male",
        "Phone": "0505050505",
        "Email": "david.property@home.co.uk",
        "PassportNumber": null,
        "DriversLicenseNumber": "PROPE123456AB8CD",
        "IdType": "driving_licence",
        "HouseNumber": "15",
        "Street": "Boundary Lane",
        "City": "Leeds",
        "County": "West Yorkshire",
        "Postcode": "LS1 4BC",
        "Country": "United Kingdom",
        "CountryCode": "GB",
        "CompanyName": null,
        "CompanyNumber": null,
        "CompanyHouseNumber": null,
        "CompanyStreet": null,
        "CompanyCity": null,
        "CompanyCounty": null,
        "CompanyPostcode": null,
        "CompanyCountry": null,
        "CompanyCountryCode": null,
        "Notes": null,
        "PaymentMethod": "card",
        "PaymentResult": "successful",
        "PaymentAmount": 3500,
        "PaymentProduct": "Property Boundary Dispute",
        "AliasId": null,
        "OrderId": null,
        "SHASign": null,
        "PaymentTimestamp": "2025-07-19T11:50:00"
      }
    ],
    "documents": [
      {
        "DocumentId": 900051,
        "InstructionRef": "HLX-10005-10005",
        "DocumentType": "property_deed",
        "FileName": "property_deeds.pdf",
        "BlobUrl": "https://example.com/property_deeds.pdf",
        "FileSizeBytes": 567890,
        "UploadedBy": "david.property@home.co.uk",
        "UploadedAt": "2025-07-19T12:00:00",
        "Notes": "Property title deeds and land registry documents"
      },
      {
        "DocumentId": 900052,
        "InstructionRef": "HLX-10005-10005",
        "DocumentType": "survey_report",
        "FileName": "boundary_survey.pdf",
        "BlobUrl": "https://example.com/boundary_survey.pdf",
        "FileSizeBytes": 1234567,
        "UploadedBy": "marie.property@home.co.uk",
        "UploadedAt": "2025-07-20T10:15:00",
        "Notes": "Professional boundary survey report"
      },
      {
        "DocumentId": 900053,
        "InstructionRef": "HLX-10005-10005",
        "DocumentType": "neighbour_correspondence",
        "FileName": "neighbour_letters.pdf",
        "BlobUrl": "https://example.com/neighbour_letters.pdf",
        "FileSizeBytes": 145678,
        "UploadedBy": "david.property@home.co.uk",
        "UploadedAt": "2025-07-19T12:05:00",
        "Notes": "Email correspondence with neighbour regarding dispute"
      }
    ],
    "riskAssessments": [
      {
        "MatterId": "m5m5m5m5-m5m5-5m5m-m5m5-m5m5m5m5m5m5",
        "InstructionRef": "HLX-10005-10005",
        "RiskAssessor": "JH",
        "ComplianceDate": "2025-07-20",
        "ComplianceExpiry": "2026-01-20",
        "ClientType": "Individual or Company registered in England and Wales with Companies House",
        "ClientType_Value": 1,
        "DestinationOfFunds": "Client within UK",
        "DestinationOfFunds_Value": 1,
        "FundsType": "Personal Cheque, BACS",
        "FundsType_Value": 1,
        "HowWasClientIntroduced": "Existing client introduction, personal introduction",
        "HowWasClientIntroduced_Value": 1,
        "Limitation": "There is greater than 6 months to the expiry of the limitation period",
        "Limitation_Value": 2,
        "SourceOfFunds": "Clients named account",
        "SourceOfFunds_Value": 1,
        "ValueOfInstruction": "£10,000 to £500,000",
        "ValueOfInstruction_Value": 2,
        "RiskAssessmentResult": "Low Risk",
        "RiskScore": 9,
        "RiskScoreIncrementBy": 0,
        "TransactionRiskLevel": "Low Risk",
        "ClientRiskFactorsConsidered": true,
        "TransactionRiskFactorsConsidered": true,
        "FirmWideAMLPolicyConsidered": true,
        "FirmWideSanctionsRiskConsidered": true
      }
    ],
    "electronicIDChecks": [],
    "idVerifications": [],
    "compliance": [],
    "matters": [],
    "opponents": []
  },
  {
    "prospectId": 5006,
    "deals": [
      {
        "DealId": 10006,
        "InstructionRef": "HLX-10006-10006",
        "ProspectId": 5006,
        "Passcode": "P1006",
        "ServiceDescription": "Corporate restructuring advice for medium-sized manufacturing company.",
        "Amount": 12000,
        "AreaOfWork": "commercial",
        "PitchedBy": "LZ",
        "PitchedDate": "2025-07-10",
        "PitchedTime": "13:00:00",
        "PitchValidUntil": "2025-08-10",
        "Status": "closed",
        "IsMultiClient": true,
        "LeadClientId": 5006,
        "LeadClientEmail": "ceo@manufacturing.co.uk",
        "CloseDate": "2025-07-16",
        "CloseTime": "16:00:00",
        "jointClients": [],
        "documents": []
      }
    ],
    "jointClients": [
      {
        "DealJointClientId": 900016,
        "DealId": 10006,
        "ClientEmail": "cfo@manufacturing.co.uk",
        "HasSubmitted": true,
        "SubmissionDateTime": "2025-07-17T09:30:00"
      },
      {
        "DealJointClientId": 900017,
        "DealId": 10006,
        "ClientEmail": "legal@manufacturing.co.uk",
        "HasSubmitted": false,
        "SubmissionDateTime": null
      }
    ],
    "instructions": [
      {
        "InstructionRef": "HLX-10006-10006",
        "Stage": "completed",
        "ClientType": "Company",
        "HelixContact": "LZ",
        "ConsentGiven": true,
        "InternalStatus": "paid",
        "SubmissionDate": "2025-07-16",
        "SubmissionTime": "16:15:00",
        "LastUpdated": "2025-07-16T16:15:00",
        "ClientId": null,
        "RelatedClientId": null,
        "MatterId": "c6c6c6c6-c6c6-6c6c-c6c6-c6c6c6c6c6c6",
        "Title": "Mr",
        "FirstName": "James",
        "LastName": "Manufacturing",
        "Nationality": "United Kingdom",
        "NationalityAlpha2": "GB",
        "DOB": "1965-08-30",
        "Gender": "Male",
        "Phone": "0606060606",
        "Email": "ceo@manufacturing.co.uk",
        "PassportNumber": null,
        "DriversLicenseNumber": null,
        "IdType": null,
        "HouseNumber": "100",
        "Street": "Industrial Park",
        "City": "Birmingham",
        "County": "West Midlands",
        "Postcode": "B12 9XY",
        "Country": "United Kingdom",
        "CountryCode": "GB",
        "CompanyName": "Manufacturing Excellence Ltd",
        "CompanyNumber": "08765432",
        "CompanyHouseNumber": "08765432",
        "CompanyStreet": "Industrial Park",
        "CompanyCity": "Birmingham",
        "CompanyCounty": "West Midlands",
        "CompanyPostcode": "B12 9XY",
        "CompanyCountry": "United Kingdom",
        "CompanyCountryCode": "GB",
        "Notes": "High-value corporate restructuring matter",
        "PaymentMethod": "card",
        "PaymentResult": "successful",
        "PaymentAmount": 12000,
        "PaymentProduct": "Corporate Restructuring Advisory",
        "AliasId": null,
        "OrderId": null,
        "SHASign": null,
        "PaymentTimestamp": "2025-07-16T16:20:00"
      }
    ],
    "documents": [
      {
        "DocumentId": 900061,
        "InstructionRef": "HLX-10006-10006",
        "DocumentType": "company_accounts",
        "FileName": "annual_accounts_2024.pdf",
        "BlobUrl": "https://example.com/annual_accounts_2024.pdf",
        "FileSizeBytes": 2345678,
        "UploadedBy": "cfo@manufacturing.co.uk",
        "UploadedAt": "2025-07-17T10:00:00",
        "Notes": "Audited annual accounts for 2024"
      },
      {
        "DocumentId": 900062,
        "InstructionRef": "HLX-10006-10006",
        "DocumentType": "memorandum_articles",
        "FileName": "memorandum_and_articles.pdf",
        "BlobUrl": "https://example.com/memorandum_and_articles.pdf",
        "FileSizeBytes": 345678,
        "UploadedBy": "legal@manufacturing.co.uk",
        "UploadedAt": "2025-07-17T11:00:00",
        "Notes": "Current memorandum and articles of association"
      }
    ],
    "riskAssessments": [
      {
        "MatterId": "c6c6c6c6-c6c6-6c6c-c6c6-c6c6c6c6c6c6",
        "InstructionRef": "HLX-10006-10006",
        "RiskAssessor": "LZ",
        "ComplianceDate": "2025-07-17",
        "ComplianceExpiry": "2026-01-17",
        "ClientType": "Group Company or Subsidiary, Trust",
        "ClientType_Value": 2,
        "DestinationOfFunds": "Client within UK",
        "DestinationOfFunds_Value": 1,
        "FundsType": "Personal Cheque, BACS",
        "FundsType_Value": 1,
        "HowWasClientIntroduced": "Internet Enquiry",
        "HowWasClientIntroduced_Value": 2,
        "Limitation": "There is no applicable limitation period",
        "Limitation_Value": 1,
        "SourceOfFunds": "Clients named account",
        "SourceOfFunds_Value": 1,
        "ValueOfInstruction": "£10,000 to £500,000",
        "ValueOfInstruction_Value": 2,
        "RiskAssessmentResult": "Medium Risk",
        "RiskScore": 10,
        "RiskScoreIncrementBy": 0,
        "TransactionRiskLevel": "Medium Risk",
        "ClientRiskFactorsConsidered": true,
        "TransactionRiskFactorsConsidered": true,
        "FirmWideAMLPolicyConsidered": true,
        "FirmWideSanctionsRiskConsidered": true
      }
    ],
    "electronicIDChecks": [],
    "idVerifications": [],
    "compliance": [],
    "matters": [],
    "opponents": []
  },
  {
    "prospectId": 5007,
    "deals": [
      {
        "DealId": 10007,
        "InstructionRef": null,
        "ProspectId": 5007,
        "Passcode": "P1007",
        "ServiceDescription": "Intellectual property licensing agreement review.",
        "Amount": 2800,
        "AreaOfWork": "intellectual_property",
        "PitchedBy": "RP",
        "PitchedDate": "2025-07-18",
        "PitchedTime": "11:00:00",
        "PitchValidUntil": "2025-08-18",
        "Status": "pitched",
        "IsMultiClient": false,
        "LeadClientId": 5007,
        "LeadClientEmail": "inventor@techstartup.com",
        "CloseDate": null,
        "CloseTime": null,
        "jointClients": [],
        "documents": []
      }
    ],
    "jointClients": [],
    "instructions": [],
    "documents": [],
    "riskAssessments": [],
    "electronicIDChecks": [],
    "idVerifications": [],
    "compliance": []
  },
  {
    "prospectId": 5008,
    "deals": [
      {
        "DealId": 10008,
        "InstructionRef": "HLX-10008-10008",
        "ProspectId": 5008,
        "Passcode": "P1008",
        "ServiceDescription": "High-stakes commercial litigation involving international contract breach.",
        "Amount": 25000,
        "AreaOfWork": "litigation",
        "PitchedBy": "LZ",
        "PitchedDate": "2025-07-14",
        "PitchedTime": "10:00:00",
        "PitchValidUntil": "2025-08-14",
        "Status": "closed",
        "IsMultiClient": true,
        "LeadClientId": 5008,
        "LeadClientEmail": "ceo@globaltrader.com",
        "CloseDate": "2025-07-21",
        "CloseTime": "09:00:00",
        "jointClients": [],
        "documents": []
      }
    ],
    "jointClients": [
      {
        "DealJointClientId": 900018,
        "DealId": 10008,
        "ClientEmail": "legal.director@globaltrader.com",
        "HasSubmitted": true,
        "SubmissionDateTime": "2025-07-21T10:00:00"
      },
      {
        "DealJointClientId": 900019,
        "DealId": 10008,
        "ClientEmail": "cfo@globaltrader.com",
        "HasSubmitted": true,
        "SubmissionDateTime": "2025-07-21T10:30:00"
      }
    ],
    "instructions": [
      {
        "InstructionRef": "HLX-10008-10008",
        "Stage": "completed",
        "ClientType": "Company",
        "HelixContact": "LZ",
        "ConsentGiven": true,
        "InternalStatus": "paid",
        "SubmissionDate": "2025-07-21",
        "SubmissionTime": "09:15:00",
        "LastUpdated": "2025-07-21T09:15:00",
        "ClientId": null,
        "RelatedClientId": null,
        "MatterId": "h8h8h8h8-h8h8-8h8h-h8h8-h8h8h8h8h8h8",
        "Title": "Ms",
        "FirstName": "Rebecca",
        "LastName": "Globaltrader",
        "Nationality": "United Kingdom",
        "NationalityAlpha2": "GB",
        "DOB": "1972-12-08",
        "Gender": "Female",
        "Phone": "0808080808",
        "Email": "ceo@globaltrader.com",
        "PassportNumber": null,
        "DriversLicenseNumber": null,
        "IdType": null,
        "HouseNumber": null,
        "Street": null,
        "City": null,
        "County": null,
        "Postcode": null,
        "Country": null,
        "CountryCode": null,
        "CompanyName": "Global Trader International Ltd",
        "CompanyNumber": "12345678",
        "CompanyHouseNumber": "12345678",
        "CompanyStreet": "Commerce House, Trade Street",
        "CompanyCity": "London",
        "CompanyCounty": "Greater London",
        "CompanyPostcode": "EC1A 1BB",
        "CompanyCountry": "United Kingdom",
        "CompanyCountryCode": "GB",
        "Notes": "High-value international litigation matter - requires enhanced due diligence",
        "PaymentMethod": "card",
        "PaymentResult": "successful",
        "PaymentAmount": 25000,
        "PaymentProduct": "International Commercial Litigation",
        "AliasId": null,
        "OrderId": null,
        "SHASign": null,
        "PaymentTimestamp": "2025-07-21T09:20:00"
      }
    ],
    "documents": [
      {
        "DocumentId": 900081,
        "InstructionRef": "HLX-10008-10008",
        "DocumentType": "contract",
        "FileName": "international_supply_agreement.pdf",
        "BlobUrl": "https://example.com/international_supply_agreement.pdf",
        "FileSizeBytes": 4567890,
        "UploadedBy": "legal.director@globaltrader.com",
        "UploadedAt": "2025-07-21T10:15:00",
        "Notes": "Original supply agreement subject to dispute"
      },
      {
        "DocumentId": 900082,
        "InstructionRef": "HLX-10008-10008",
        "DocumentType": "correspondence",
        "FileName": "breach_notices.pdf",
        "BlobUrl": "https://example.com/breach_notices.pdf",
        "FileSizeBytes": 789012,
        "UploadedBy": "legal.director@globaltrader.com",
        "UploadedAt": "2025-07-21T10:20:00",
        "Notes": "Formal breach notices and correspondence"
      },
      {
        "DocumentId": 900083,
        "InstructionRef": "HLX-10008-10008",
        "DocumentType": "financial_statements",
        "FileName": "loss_calculations.xlsx",
        "BlobUrl": "https://example.com/loss_calculations.xlsx",
        "FileSizeBytes": 234567,
        "UploadedBy": "cfo@globaltrader.com",
        "UploadedAt": "2025-07-21T10:45:00",
        "Notes": "Financial impact and loss calculations"
      }
    ],
    "riskAssessments": [
      {
        "MatterId": "h8h8h8h8-h8h8-8h8h-h8h8-h8h8h8h8h8h8",
        "InstructionRef": "HLX-10008-10008",
        "RiskAssessor": "LZ",
        "ComplianceDate": "2025-07-21",
        "ComplianceExpiry": "2026-01-21",
        "ClientType": "Non UK Company",
        "ClientType_Value": 3,
        "DestinationOfFunds": "Outwith UK or Client outwith EU",
        "DestinationOfFunds_Value": 3,
        "FundsType": "Personal Cheque, BACS",
        "FundsType_Value": 1,
        "HowWasClientIntroduced": "Other",
        "HowWasClientIntroduced_Value": 3,
        "Limitation": "There is less than 6 months to limitation expiry",
        "Limitation_Value": 3,
        "SourceOfFunds": "Any other account",
        "SourceOfFunds_Value": 3,
        "ValueOfInstruction": "Above £500,000",
        "ValueOfInstruction_Value": 3,
        "RiskAssessmentResult": "High Risk",
        "RiskScore": 19,
        "RiskScoreIncrementBy": 0,
        "TransactionRiskLevel": "High Risk",
        "ClientRiskFactorsConsidered": true,
        "TransactionRiskFactorsConsidered": true,
        "FirmWideAMLPolicyConsidered": true,
        "FirmWideSanctionsRiskConsidered": true
      }
    ],
    "electronicIDChecks": [],
    "idVerifications": [],
    "compliance": [],
    "matters": [],
    "opponents": [
      {
        "OpponentID": "L8901234-L890-4890-L890-L890L890L890",
        "PartyRole": "Defendant",
        "IsCompany": true,
        "Title": null,
        "FirstName": null,
        "LastName": null,
        "CompanyName": "European Supply Chain GmbH",
        "CompanyNumber": "DE-123456789",
        "Email": "legal@europeansupply.de",
        "Phone": "+49301234567",
        "HouseNumber": "45",
        "Street": "Industriestrasse",
        "City": "Berlin",
        "County": "Brandenburg",
        "Postcode": "10115",
        "Country": "Germany"
      }
    ]
  },
  {
    "prospectId": 5004,
    "deals": [
      {
        "DealId": 10004,
        "InstructionRef": "HLX-10004-10004",
        "ProspectId": 5004,
        "Passcode": "P1004",
        "ServiceDescription": "Advice and representation in relation to an adjudication dispute.",
        "Amount": 4000,
        "AreaOfWork": "construction",
        "PitchedBy": "LZ",
        "PitchedDate": "2025-07-12",
        "PitchedTime": "14:00:00",
        "PitchValidUntil": "2025-08-12",
        "Status": "closed",
        "IsMultiClient": true,
        "LeadClientId": 5003,
        "LeadClientEmail": "lead3@example.com",
        "CloseDate": "2025-07-13",
        "CloseTime": "10:00:00",
        "jointClients": [
          {
            "DealJointClientId": 900013,
            "DealId": 10004,
            "ClientEmail": "joint3a@example.com",
            "Name": "Alice Smith",
            "FirstName": "Alice",
            "LastName": "Smith",
            "HasSubmitted": "1"
          },
          {
            "DealJointClientId": 900014,
            "DealId": 10004,
            "ClientEmail": "joint3b@example.com",
            "Name": "Bob Jones",
            "FirstName": "Bob",
            "LastName": "Jones",
            "HasSubmitted": "1"
          }
        ],
        "documents": []
      }
    ],
    "jointClients": [],
    "instructions": [
      {
        "InstructionRef": "HLX-10004-10004",
        "Stage": "completed",
        "ClientType": "Individual",
        "HelixContact": "LZ",
        "ConsentGiven": true,
        "InternalStatus": "paid",
        "SubmissionDate": "2025-07-13",
        "SubmissionTime": "10:30:00",
        "LastUpdated": "2025-07-13T10:30:00",
        "ClientId": null,
        "RelatedClientId": null,
        "MatterId": "HLX-10004-10004",
        "Title": null,
        "FirstName": "Charlie",
        "LastName": "Construction",
        "Nationality": "United Kingdom",
        "NationalityAlpha2": "GB",
        "DOB": "1980-03-15",
        "Gender": "Male",
        "Phone": "0303030303",
        "Email": "lead3@example.com",
        "PassportNumber": "987654321",
        "DriversLicenseNumber": null,
        "IdType": "passport",
        "HouseNumber": "15",
        "Street": "Builder Street",
        "City": "London",
        "County": "Greater London",
        "Postcode": "SW1 1AA",
        "Country": "United Kingdom",
        "CountryCode": "GB",
        "CompanyName": "Construction Solutions Ltd",
        "CompanyNumber": "12345678",
        "CompanyHouseNumber": "12345678",
        "CompanyStreet": "Business Park",
        "CompanyCity": "London",
        "CompanyCounty": "Greater London",
        "CompanyPostcode": "SW1 1BB",
        "CompanyCountry": "United Kingdom",
        "CompanyCountryCode": "GB",
        "Notes": "Multi-client construction dispute matter",
        "PaymentMethod": "card",
        "PaymentResult": "successful",
        "PaymentAmount": 4000,
        "PaymentProduct": "Construction Adjudication Dispute",
        "AliasId": null,
        "OrderId": null,
        "SHASign": null,
        "PaymentTimestamp": null
      },
      {
        "InstructionRef": "HLX-00000-P1003",
        "Stage": "completed",
        "ClientType": "Joint",
        "HelixContact": "LZ",
        "ConsentGiven": true,
        "InternalStatus": "paid",
        "SubmissionDate": "2025-07-13",
        "SubmissionTime": "11:00:00",
        "LastUpdated": "2025-07-13T11:00:00",
        "ClientId": null,
        "RelatedClientId": null,
        "MatterId": null,
        "Title": null,
        "FirstName": "Alice",
        "LastName": "Smith",
        "Nationality": "United Kingdom",
        "NationalityAlpha2": "GB",
        "DOB": "1985-07-22",
        "Gender": "Female",
        "Phone": "0313131313",
        "Email": "joint3a@example.com",
        "PassportNumber": "876543210",
        "DriversLicenseNumber": null,
        "IdType": "passport",
        "HouseNumber": "22",
        "Street": "Joint Street",
        "City": "London",
        "County": "Greater London",
        "Postcode": "SW1 2AA",
        "Country": "United Kingdom",
        "CountryCode": "GB",
        "CompanyName": null,
        "CompanyNumber": null,
        "CompanyHouseNumber": null,
        "CompanyStreet": null,
        "CompanyCity": null,
        "CompanyCounty": null,
        "CompanyPostcode": null,
        "CompanyCountry": null,
        "CompanyCountryCode": null,
        "Notes": "Joint client for construction dispute",
        "PaymentMethod": null,
        "PaymentResult": null,
        "PaymentAmount": null,
        "PaymentProduct": null,
        "AliasId": null,
        "OrderId": null,
        "SHASign": null,
        "PaymentTimestamp": null
      },
      {
        "InstructionRef": "HLX-00000-P1003",
        "Stage": "completed",
        "ClientType": "Joint",
        "HelixContact": "LZ",
        "ConsentGiven": true,
        "InternalStatus": "paid",
        "SubmissionDate": "2025-07-13",
        "SubmissionTime": "11:30:00",
        "LastUpdated": "2025-07-13T11:30:00",
        "ClientId": null,
        "RelatedClientId": null,
        "MatterId": null,
        "Title": null,
        "FirstName": "Bob",
        "LastName": "Jones",
        "Nationality": "United Kingdom",
        "NationalityAlpha2": "GB",
        "DOB": "1978-11-08",
        "Gender": "Male",
        "Phone": "0323232323",
        "Email": "joint3b@example.com",
        "PassportNumber": null,
        "DriversLicenseNumber": "JONES789123AB9CD",
        "IdType": "driving_licence",
        "HouseNumber": "33",
        "Street": "Another Street",
        "City": "London",
        "County": "Greater London",
        "Postcode": "SW1 3AA",
        "Country": "United Kingdom",
        "CountryCode": "GB",
        "CompanyName": null,
        "CompanyNumber": null,
        "CompanyHouseNumber": null,
        "CompanyStreet": null,
        "CompanyCity": null,
        "CompanyCounty": null,
        "CompanyPostcode": null,
        "CompanyCountry": null,
        "CompanyCountryCode": null,
        "Notes": "Joint client for construction dispute",
        "PaymentMethod": null,
        "PaymentResult": null,
        "PaymentAmount": null,
        "PaymentProduct": null,
        "AliasId": null,
        "OrderId": null,
        "SHASign": null,
        "PaymentTimestamp": null
      }
    ],
    "documents": [],
    "riskAssessments": [],
    "electronicIDChecks": [],
    "idVerifications": [],
    "compliance": []
  }
]